[
  {
    "file": "(14 封私信  15 条消息) 可以在家干的兼职有哪些？ - 知乎.md",
    "len": 11960
  },
  {
    "file": "003-互联网的人际拓展方法.md",
    "len": 3857
  },
  {
    "file": "030天 平民进阶的核心秘诀.md",
    "len": 5839
  },
  {
    "file": "1.基本法则 激励、稀缺、多面性.md",
    "len": 4036
  },
  {
    "file": "1年赚了80万，我只凭这两个字 - 87副业-87副业.md",
    "len": 4468
  },
  {
    "file": "20190113《睡眠革命》——樊登读书会读书笔记.md",
    "len": 9497
  },
  {
    "file": "2021-1-2●赚钱欲望。说干就干干脆点，这很爽。我性格里面的缺陷。从问题到推解决方法。.md",
    "len": 5083
  },
  {
    "file": "2023最新最全科学上网指南，上外网有什么好玩的？机场推荐与测评。 - 爱远眺.md",
    "len": 11923
  },
  {
    "file": "20年前没买房、没下海，20年后怎样才能不后悔？-虎嗅网.md",
    "len": 8501
  },
  {
    "file": "3 分钟找书指南 v6.0.md",
    "len": 5780
  },
  {
    "file": "500个逼婚父母：脱单、脱贫和滚，求求你选一个.md",
    "len": 2988
  },
  {
    "file": "5R笔记法_百度百科.md",
    "len": 3099
  },
  {
    "file": "EasyU(优启通) v3.7.2022.0527 VIP版 - 果核剥壳.md",
    "len": 2403
  },
  {
    "file": "Edgeless(强大的PE工具) Beta4.1.0 - 果核剥壳.md",
    "len": 4402
  },
  {
    "file": "Evernote 教你彻底活用笔记链接：整理笔记最有效的 7 个案例  印象笔记博客.md",
    "len": 5348
  },
  {
    "file": "FirPE 维护系统 v1.8.1 - 果核剥壳.md",
    "len": 3365
  },
  {
    "file": "i73 - 文库下载.md",
    "len": 4583
  },
  {
    "file": "Notion – The all-in-one workspace for your notes, tasks, wikis, and databases.md",
    "len": 2784
  },
  {
    "file": "PUA的本质是啥？它是如何给人洗脑的，为何全网围剿封杀PUA？（魔道之死 围杀PUA）  设计笔记.md",
    "len": 9800
  },
  {
    "file": "Windows 10 企业版2021 LTSC 21H2 Build 19044.1806 - 果核剥壳.md",
    "len": 2805
  },
  {
    "file": "●2021-1-1.一见钟情是见色起意，日久生情是权衡利弊。主动找对去不舒服的场地。物质财富自由，打破环境束缚。年收入小10万。.md",
    "len": 3704
  },
  {
    "file": "●●变强大吧——如何成为一个更强大的人.md",
    "len": 5381
  },
  {
    "file": "●●走出舒适，进入学习区.md",
    "len": 2982
  },
  {
    "file": "✔比尔·盖茨22岁女儿火了：原来有钱到一定程度，根本就不需要炫富-体育频道-手机搜狐.md",
    "len": 12741
  },
  {
    "file": "《天才是训练出来的》读后感 2010-12-04 2104阅读： 一口气读完了薛涌的新作《天才是训练出来的》。上卷《天才论》令我心潮澎湃，为天才们的特殊天赋所折服；在看中卷《培养论》后半部分和下卷《行动示例》时，我时常与薛涌的观点产生强烈的共鸣，特别是以下两段文字： 在社会人才这个领域，很少有人知道自己真正的才能。那些锲而不舍的人尽管不停地转化行当、落魄很久，却_011510.md",
    "len": 2399
  },
  {
    "file": "《天才是训练出来的》读后感 2010-12-04 2104阅读： 一口气读完了薛涌的新作《天才是训练出来的》。上卷《天才论》令我心潮澎湃，为天才们的特殊天赋所折服；在看中卷《培养论》后半部分和下卷《行动示例》时，我时常与薛涌的观点产生强烈的共鸣，特别是以下两段文字： 在社会人才这个领域，很少有人知道自己真正的才能。那些锲而不舍的人尽管不停地转化行当、落魄很久，却_ca207e.md",
    "len": 2399
  },
  {
    "file": "【实用干货】印象笔记模板大全  印象笔记博客.md",
    "len": 2408
  },
  {
    "file": "【年少轻狂】 Win7 集成补丁版本 2022.04 - 果核剥壳.md",
    "len": 4727
  },
  {
    "file": "【果核】Windows 10 Pro 21H2(19044.1826) 优化精简版 - 果核剥壳.md",
    "len": 3204
  },
  {
    "file": "【聊天泡妹子课程】最全撩妹+相亲课程+聊天搭讪技巧 百度云盘资源下载 - EMLOG-曾子资源.1.md",
    "len": 4247
  },
  {
    "file": "【聊天泡妹子课程】最全撩妹+相亲课程+聊天搭讪技巧 百度云盘资源下载 - EMLOG-曾子资源.md",
    "len": 3939
  },
  {
    "file": "【聊天泡妹子课程】最全撩妹+相亲课程+聊天搭讪技巧 百度云盘资源下载.md",
    "len": 2542
  },
  {
    "file": "不在状态怎么办呢.md",
    "len": 7012
  },
  {
    "file": "不想上班？ 很迷茫？.md",
    "len": 4177
  },
  {
    "file": "不能趁早领悟这些点，只能继续当不赚钱的傻逼.1.md",
    "len": 3708
  },
  {
    "file": "不能趁早领悟这些点，只能继续当不赚钱的傻逼.md",
    "len": 3696
  },
  {
    "file": "不追热点，只做对的事.md",
    "len": 3169
  },
  {
    "file": "专科生和本科生的差距到底在哪？ - ApplySquare.md",
    "len": 2221
  },
  {
    "file": "个人生活年度复盘模板.md",
    "len": 2052
  },
  {
    "file": "为什么不运动就可以减肥  「许岑谈减肥」音频内容正式上线.md",
    "len": 5304
  },
  {
    "file": "为什么你懂得那么多道理，还是不赚钱？.md",
    "len": 2871
  },
  {
    "file": "为什么年龄越大感觉时间过得越快？  內酷网.md",
    "len": 3593
  },
  {
    "file": "为什么真正优秀的人，大都不合群？_人生感悟.md",
    "len": 4571
  },
  {
    "file": "为什么要早起？这是我听过最牛的答案.md",
    "len": 3509
  },
  {
    "file": "习近平给出信号：中国开放的大门只会越开越大-虎嗅网.md",
    "len": 7471
  },
  {
    "file": "什么是美？什么是好？维护想象创造想象。.md",
    "len": 3230
  },
  {
    "file": "任正非为什么要对华为新鲜人讲“汉语拼音之父”周有光？-虎嗅网.md",
    "len": 5036
  },
  {
    "file": "任正非：我们要在攀登珠峰的征程中沿途下蛋-虎嗅网.md",
    "len": 4400
  },
  {
    "file": "何苦以房养老.md",
    "len": 6789
  },
  {
    "file": "你信仰什么，生命就走向什么！.md",
    "len": 3836
  },
  {
    "file": "你有一份小红书卖虚拟资料SOP运营手册待查收  人人都是产品经理.md",
    "len": 5106
  },
  {
    "file": "内行人说  自从学了这个专业，我就看淡了这个世界.md",
    "len": 4616
  },
  {
    "file": "再来一次，我会放弃北大-虎嗅网.md",
    "len": 4616
  },
  {
    "file": "再见，抖音！国家正式发声！.md",
    "len": 4262
  },
  {
    "file": "千城4 和 我要戴上有颜色的眼镜 的聊天记录.md",
    "len": 7450
  },
  {
    "file": "印象笔记的用法和最新动态  印象笔记博客.md",
    "len": 5061
  },
  {
    "file": "原来用讯飞语记可以打通写作的任督二脉，一小时写一万字 - 简书.md",
    "len": 2513
  },
  {
    "file": "同样是大学，为什么专科念三年，本科念四年？-教育频道-手机搜狐.md",
    "len": 2165
  },
  {
    "file": "哈佛大学研究：一个人成为废物的九大根源.md",
    "len": 2548
  },
  {
    "file": "唐驳虎：塑型未来中国？京沪突然加入战局！.md",
    "len": 8530
  },
  {
    "file": "国人都羡慕西方女人丰满身材、为何很少有外国美女嫁到中国.md",
    "len": 3615
  },
  {
    "file": "国际流行学生站式学习，身体健康提高成绩两不误 - 知乎.md",
    "len": 3569
  },
  {
    "file": "图片.md",
    "len": 4926
  },
  {
    "file": "在家躺着拿工资，是挺过意不去的.md",
    "len": 7326
  },
  {
    "file": "在线抠图 - 不死鸟 - 分享为王官网.md",
    "len": 2916
  },
  {
    "file": "处理进度记录.md",
    "len": 4998
  },
  {
    "file": "多看效应：揭秘日久生情的真相，为什么有人越看越顺眼。.md",
    "len": 2378
  },
  {
    "file": "大人的童心-虎嗅网.md",
    "len": 5341
  },
  {
    "file": "大学毕业后，迷茫未来该做什么？你可以看看这个视频.md",
    "len": 6806
  },
  {
    "file": "天才是训练出来的。.md",
    "len": 2187
  },
  {
    "file": "女人最不需要的，就是女人味.md",
    "len": 5489
  },
  {
    "file": "好。把网页变得更快。.md",
    "len": 3025
  },
  {
    "file": "如何做「读书笔记」收获最大？  印象笔记博客.md",
    "len": 2895
  },
  {
    "file": "如何提高睡眠质量，减短睡眠时间？ - 知乎.md",
    "len": 9358
  },
  {
    "file": "如何表白才刚刚好？.md",
    "len": 3429
  },
  {
    "file": "如何解释人际交往中的「六度空间」理论，它是如何证明的？ - 知乎.md",
    "len": 5614
  },
  {
    "file": "孟羽童离职冲上热搜！成为值钱员工的5层修炼，你在哪一层？.md",
    "len": 9735
  },
  {
    "file": "学习女德才有未来.md",
    "len": 2797
  },
  {
    "file": "富人定律：你要假装很有钱！.md",
    "len": 5143
  },
  {
    "file": "小扎又被议员们“蹂躏”了5个小时-虎嗅网.md",
    "len": 2706
  },
  {
    "file": "小鸽分享：20款伪原创（智能写作）工具和软件 - 知乎.md",
    "len": 3489
  },
  {
    "file": "年底了，和许久未见的亲戚朋友找不到聊天话题？关于聊天的真相是怎样的？ - 知乎.md",
    "len": 4851
  },
  {
    "file": "年轻人缺乏性趣的日子-虎嗅网.md",
    "len": 5214
  },
  {
    "file": "张一鸣只是想要一个微博杀手-虎嗅网.md",
    "len": 11172
  },
  {
    "file": "张维迎：没有思想市场，世界会怎么样？-虎嗅网.md",
    "len": 7848
  },
  {
    "file": "当你不想写稿了，这几款「智能写作工具」能帮上忙吗？  爱范儿.md",
    "len": 10009
  },
  {
    "file": "当变态跟踪狂顺着网线爬进你家-虎嗅网.md",
    "len": 4197
  },
  {
    "file": "得到听书.md",
    "len": 3624
  },
  {
    "file": "微信私域流量惊魂  一周收藏排行.md",
    "len": 5770
  },
  {
    "file": "微美文微博上说，十开头的年龄，太容易为爱奋不顾身。.md",
    "len": 2980
  },
  {
    "file": "必须要承认，我们的底气来源于流量.1.md",
    "len": 2555
  },
  {
    "file": "必须要承认，我们的底气来源于流量.md",
    "len": 2547
  },
  {
    "file": "快手小游戏.md",
    "len": 2632
  },
  {
    "file": "怎么读书.md",
    "len": 9342
  },
  {
    "file": "思维导图笔记.md",
    "len": 2711
  },
  {
    "file": "想要提高效率，就得不公平 « 学而时嘻之.md",
    "len": 6226
  },
  {
    "file": "成为“别人家的爸爸”有感.md",
    "len": 4246
  },
  {
    "file": "成功者素质.md",
    "len": 5148
  },
  {
    "file": "成龙首次承认嫖娼、出轨、家暴，65岁的他真的老了.md",
    "len": 10542
  },
  {
    "file": "我们为何还在讨好白种人？.md",
    "len": 5885
  },
  {
    "file": "我想，我需要无限痛苦。.md",
    "len": 2683
  },
  {
    "file": "我把自己的生活变成「游戏系统」，达成了这些欲望：买 iPad、Kindle…….md",
    "len": 7212
  },
  {
    "file": "我的ruler，不是loser.md",
    "len": 3302
  },
  {
    "file": "所有父母必须接受的残酷真相：你的付出，99%是没用的.md",
    "len": 4108
  },
  {
    "file": "手把手教你怎么「洗稿」，.md",
    "len": 6246
  },
  {
    "file": "找法网.md",
    "len": 6011
  },
  {
    "file": "技能学习与认知拓展。.md",
    "len": 2854
  },
  {
    "file": "把它做成思维导图，然后弄成一个系列吧，这是我的IP。欢迎来到世界观方法论。.md",
    "len": 9480
  },
  {
    "file": "抖音和小红书，越来越反常识了。.md",
    "len": 4663
  },
  {
    "file": "抖音火了，短视频创业者们该补补课啦-虎嗅网.md",
    "len": 5822
  },
  {
    "file": "抖音网红、10万+大号都在用的沙雕段子，是这样来的-36氪.md",
    "len": 12252
  },
  {
    "file": "抖音，互联网时代的三俗农村聚集地 - 简书.md",
    "len": 3364
  },
  {
    "file": "抽几分钟时间看完，绝对有用.md",
    "len": 2823
  },
  {
    "file": "推荐五款能永久免费使用的梯子，电脑手机均可，稳定流畅｜欣傳媒.1.md",
    "len": 3253
  },
  {
    "file": "推荐五款能永久免费使用的梯子，电脑手机均可，稳定流畅｜欣傳媒.md",
    "len": 3204
  },
  {
    "file": "揭秘传x成交法，已经被广泛应用到各个领域.md",
    "len": 3832
  },
  {
    "file": "播放量超1亿！施瓦辛格2018年末超励志演讲：这才是成功的真谛.md",
    "len": 5632
  },
  {
    "file": "改变人生的秘诀：在早晨8点前做这8件事-36氪.md",
    "len": 6225
  },
  {
    "file": "教科书级的公关素材：扎克伯格逃过一劫，互联网行业游戏规则会否生变？-虎嗅网.md",
    "len": 3776
  },
  {
    "file": "教育是如何有计划的大规模制造人渣？.md",
    "len": 7632
  },
  {
    "file": "数学笔记（初级版）.md",
    "len": 5116
  },
  {
    "file": "断舍离收纳：先从这100件物品开始扔吧！.md",
    "len": 2166
  },
  {
    "file": "无标题笔记.168.md",
    "len": 7846
  },
  {
    "file": "无标题笔记.187.md",
    "len": 2282
  },
  {
    "file": "无标题笔记.244.md",
    "len": 3399
  },
  {
    "file": "无标题笔记.246.md",
    "len": 5768
  },
  {
    "file": "无标题笔记.249.md",
    "len": 3804
  },
  {
    "file": "无标题笔记.267.md",
    "len": 2382
  },
  {
    "file": "无标题笔记.274.md",
    "len": 4229
  },
  {
    "file": "无标题笔记.284.md",
    "len": 2216
  },
  {
    "file": "无标题笔记.289.md",
    "len": 4627
  },
  {
    "file": "无标题笔记.39.md",
    "len": 6796
  },
  {
    "file": "无标题笔记.80.md",
    "len": 3976
  },
  {
    "file": "普通人如何通过项目实战，成为自由职业？.md",
    "len": 7199
  },
  {
    "file": "普通人快速崛起的十大狠招（剽悍一只猫） - 土匪刘小姐 - 简书.md",
    "len": 6512
  },
  {
    "file": "普通草根年入百万.1.md",
    "len": 3938
  },
  {
    "file": "普通草根年入百万.md",
    "len": 4076
  },
  {
    "file": "有了这“7+1”个网站，我的工作效率提高了不止3倍！.md",
    "len": 7290
  },
  {
    "file": "有手机的网络时代，这很多.md",
    "len": 4069
  },
  {
    "file": "有道云笔记.md",
    "len": 8591
  },
  {
    "file": "本站Windows激活服务器上线 四句代码激活Windows.md",
    "len": 6263
  },
  {
    "file": "李笑来：我对时间与财富的新思考.md",
    "len": 9320
  },
  {
    "file": "核心主题汇总（自媒体选题库）.md",
    "len": 5258
  },
  {
    "file": "樊登读书会——低风险创业。.md",
    "len": 2676
  },
  {
    "file": "模板创意大赛结果揭晓，我们从500个作品中选出了15个超实用模板.md",
    "len": 7024
  },
  {
    "file": "残酷底层物语：一个视频软件的中国农村.md",
    "len": 7459
  },
  {
    "file": "比高项目研习社⑭群 微信群的聊天记录.md",
    "len": 5515
  },
  {
    "file": "没有“时间商”的自律都是耍流氓.md",
    "len": 5684
  },
  {
    "file": "浅谈虚拟资料电商放大收益的多种方法.md",
    "len": 4047
  },
  {
    "file": "特殊两性关系实验：心理学家告诉你，爱要怎么做.md",
    "len": 7737
  },
  {
    "file": "理想与现实之间的差距.md",
    "len": 3566
  },
  {
    "file": "生财有术网页版.md",
    "len": 12107
  },
  {
    "file": "用了 6 年印象笔记，我都用它做哪些事，以及，不用它做哪些事 - 为程序员服务.md",
    "len": 7277
  },
  {
    "file": "用思维导图提升脑力，你的大脑超乎你想象.md",
    "len": 6756
  },
  {
    "file": "番茄工作法：保持专注的最有效方法原创： 生命壹号.md",
    "len": 6355
  },
  {
    "file": "相似网站推荐服务，探索更多精彩的网络服务-要福利，就在第一福利！.md",
    "len": 6566
  },
  {
    "file": "相当于怎么做人。.md",
    "len": 7769
  },
  {
    "file": "真正强大的人，从不把优越感写在脸上.md",
    "len": 4435
  },
  {
    "file": "知乎热门：你从哪一刻起决定不再善良？.md",
    "len": 5148
  },
  {
    "file": "知乎问答：2200 ~ 600 睡眠比 200 ~ 1000 更健康吗？.md",
    "len": 3407
  },
  {
    "file": "知识星球  深度连接铁杆粉丝，运营高品质社群，知识变现的工具.1.md",
    "len": 6959
  },
  {
    "file": "离婚大数据曝光让人心寒，是什么谋杀了你的爱情.md",
    "len": 4157
  },
  {
    "file": "私域搞钱，月入3-4万【祖】.md",
    "len": 3854
  },
  {
    "file": "笔记进步大赛本周名次排行榜.md",
    "len": 7533
  },
  {
    "file": "精神生活，自我成长.md",
    "len": 9938
  },
  {
    "file": "系统升级，计算机思维看最近.md",
    "len": 2101
  },
  {
    "file": "终极，透析万物，觉醒.md",
    "len": 5381
  },
  {
    "file": "给大家看1张截图.md",
    "len": 5762
  },
  {
    "file": "美貌大王许岑的挣钱史.md",
    "len": 7679
  },
  {
    "file": "群里一直问 XX 文库怎么下载，我找了 5 个方法.md",
    "len": 4257
  },
  {
    "file": "耶鲁校长2018毕业演讲：跳出狭窄的朋友圈，画一个更广阔的圈-虎嗅网.md",
    "len": 5061
  },
  {
    "file": "致现在的我  来自5年后的自己.md",
    "len": 3356
  },
  {
    "file": "花14年追踪168对夫妻：什么样的婚姻拥有终极安全感？.md",
    "len": 7961
  },
  {
    "file": "行业分析研究报告哪里寻，试试这9个网站！  设计笔记.1.md",
    "len": 9289
  },
  {
    "file": "行业分析研究报告哪里寻，试试这9个网站！  设计笔记.md",
    "len": 12587
  },
  {
    "file": "表扬与批评孩子的技巧-爱问教育.md",
    "len": 3490
  },
  {
    "file": "被我删除的一篇文章，速看.md",
    "len": 4325
  },
  {
    "file": "裸体偷窥、监听定位，请留意那些不起眼的小物件-虎嗅网.md",
    "len": 4652
  },
  {
    "file": "记忆方法.md",
    "len": 2172
  },
  {
    "file": "试用过248款App后，这5个应用和「印象笔记」“堪称绝配”！.md",
    "len": 5877
  },
  {
    "file": "读书的成本，确实太高了-虎嗅网.md",
    "len": 3904
  },
  {
    "file": "调教百度，把百度安排得明明白白的！.md",
    "len": 6667
  },
  {
    "file": "资源下载.md",
    "len": 3255
  },
  {
    "file": "赚钱其实是一件很傻逼的事 （随笔8）.md",
    "len": 3772
  },
  {
    "file": "越败家越富有？特朗普：钱花不完的痛苦你不懂.md",
    "len": 5904
  },
  {
    "file": "迷茫的我 迷茫的你.md",
    "len": 5106
  },
  {
    "file": "选对方向的努力，比努力本身重要.md",
    "len": 3563
  },
  {
    "file": "那位成功逆袭的同学悄悄告诉我，这个世界的满分其实是78分.md",
    "len": 3840
  },
  {
    "file": "长评论的力量。商家卖东西的心理学。其实可以弄的视频说说的，可以写这文章说说的。.md",
    "len": 2732
  },
  {
    "file": "防雨？那不是事！我这衣服就差能防弹了.md",
    "len": 7927
  },
  {
    "file": "阿里出品的这4款良心工具，堪称神器! 一周收藏排行.md",
    "len": 6928
  },
  {
    "file": "雷军：公司这事若出问题，基本就万劫不复-虎嗅网.1.md",
    "len": 9671
  },
  {
    "file": "雷军：公司这事若出问题，基本就万劫不复-虎嗅网.md",
    "len": 9671
  },
  {
    "file": "音乐世界.md",
    "len": 4838
  },
  {
    "file": "颠覆者小米  一周收藏排行.md",
    "len": 6501
  },
  {
    "file": "马云：一年后的今天，我将辞去阿里巴巴董事局主席-虎嗅网.md",
    "len": 3380
  },
  {
    "file": "高手是持续性自律，你是间歇式自虐.md",
    "len": 3544
  },
  {
    "file": "高手是持续性自律，你是间歇性自虐.md",
    "len": 4669
  },
  {
    "file": "高手的战略.md",
    "len": 5943
  },
  {
    "file": "高效笔记术之康奈尔笔记5R - 寒冰2018 - 简书.md",
    "len": 2208
  },
  {
    "file": "🥃 极简创业丨平民创业进阶社群 微信群的聊天记录.md",
    "len": 3059
  },
  {
    "file": "🥃 极简创业丨让创业变得更简单 微信群的聊天记录.1.md",
    "len": 4820
  },
  {
    "file": "🥃 极简创业丨让创业变得更简单 微信群的聊天记录.10.md",
    "len": 4332
  },
  {
    "file": "🥃 极简创业丨让创业变得更简单 微信群的聊天记录.2.md",
    "len": 5260
  },
  {
    "file": "🥃 极简创业丨让创业变得更简单 微信群的聊天记录.3.md",
    "len": 4504
  },
  {
    "file": "🥃 极简创业丨让创业变得更简单 微信群的聊天记录.4.md",
    "len": 2000
  },
  {
    "file": "🥃 极简创业丨让创业变得更简单 微信群的聊天记录.5.md",
    "len": 6137
  },
  {
    "file": "🥃 极简创业丨让创业变得更简单 微信群的聊天记录.7.md",
    "len": 4159
  },
  {
    "file": "🥃 极简创业丨让创业变得更简单 微信群的聊天记录.9.md",
    "len": 6134
  },
  {
    "file": "（实战）如何让自己说话变得风趣幽默_百度经验.md",
    "len": 3297
  }
]